{
  "version": 1,
  "notes": "",
  "documentation": "\"This file is a QMK Configurator export. You can import this at <https://config.qmk.fm>. It can also be used directly with QMK's source code.\n\nTo setup your QMK environment check out the tutorial: <https://docs.qmk.fm/#/newbs>\n\nYou can convert this file to a keymap.c using this command: `qmk json2c {keymap}`\n\nYou can compile this keymap using this command: `qmk compile {keymap}`\"\n",
  "keyboard": "planck/rev6",
  "keymap": "planck_rev6_layout_planck_1x2uc_mine",
  "layout": "LAYOUT_ortho_4x12",
  "layers": [
    [
      "LT(10,KC_TAB)",
      "KC_Q",
      "KC_W",
      "KC_F",
      "KC_P",
      "KC_G",
      "KC_J",
      "KC_L",
      "KC_U",
      "KC_Y",
      "ANY(QWERTY)",
      "KC_DEL",
      "LT(5,KC_ESC)",
      "LGUI_T(KC_A)",
      "LALT_T(KC_R)",
      "LSFT_T(KC_S)",
      "LCTL_T(KC_T)",
      "KC_D",
      "KC_H",
      "LCTL_T(KC_N)",
      "RSFT_T(KC_E)",
      "LALT_T(KC_I)",
      "LGUI_T(KC_O)",
      "LT(6,KC_ENT)",
      "KC_NO",
      "KC_Z",
      "KC_X",
      "KC_C",
      "KC_V",
      "KC_B",
      "KC_K",
      "KC_M",
      "KC_COMM",
      "KC_DOT",
      "KC_SLSH",
      "KC_CAPS",
      "KC_NO",
      "KC_NO",
      "TG(9)",
      "KC_NO",
      "ANY(LOWER)",
      "KC_SPC",
      "KC_BSPC",
      "ANY(RAISE)",
      "KC_NO",
      "KC_NO",
      "KC_NO",
      "KC_NO"
    ],
    [
      "KC_TRNS",
      "KC_Q",
      "KC_W",
      "KC_E",
      "KC_R",
      "KC_T",
      "KC_Y",
      "KC_U",
      "KC_I",
      "KC_O",
      "KC_TRNS",
      "KC_TRNS",
      "KC_TRNS",
      "LGUI_T(KC_A)",
      "LALT_T(KC_S)",
      "LSFT_T(KC_D)",
      "LCTL_T(KC_F)",
      "KC_G",
      "KC_H",
      "LCTL_T(KC_J)",
      "RSFT_T(KC_K)",
      "LALT_T(KC_L)",
      "LGUI_T(KC_P)",
      "KC_TRNS",
      "KC_TRNS",
      "KC_Z",
      "KC_X",
      "KC_C",
      "KC_V",
      "KC_B",
      "KC_N",
      "KC_M",
      "KC_COMM",
      "KC_DOT",
      "KC_SLSH",
      "KC_TRNS",
      "KC_TRNS",
      "KC_TRNS",
      "KC_TRNS",
      "KC_TRNS",
      "KC_TRNS",
      "KC_TRNS",
      "KC_TRNS",
      "KC_TRNS",
      "KC_TRNS",
      "KC_TRNS",
      "KC_TRNS",
      "KC_TRNS"
    ],
    [
      "KC_TRNS",
      "KC_TILD",
      "KC_LT",
      "KC_EQL",
      "KC_GT",
      "KC_HASH",
      "KC_PERC",
      "KC_PIPE",
      "KC_AMPR",
      "KC_GRV",
      "KC_ASTR",
      "ANY(TOGGLE)",
      "KC_TRNS",
      "LGUI_T(KC_DOT)",
      "LALT_T(KC_COMM)",
      "LSFT_T(KC_9)",
      "LCTL_T(KC_0)",
      "KC_AT",
      "KC_MINS",
      "LCTL_T(KC_1)",
      "RSFT_T(KC_SLSH)",
      "LALT_T(KC_QUOT)",
      "LGUI_T(KC_SCLN)",
      "KC_TRNS",
      "KC_TRNS",
      "KC_TRNS",
      "KC_TRNS",
      "KC_TRNS",
      "KC_TRNS",
      "KC_TRNS",
      "KC_TRNS",
      "KC_TRNS",
      "KC_TRNS",
      "KC_TRNS",
      "KC_BSLS",
      "KC_TRNS",
      "KC_TRNS",
      "KC_TRNS",
      "KC_TRNS",
      "KC_TRNS",
      "KC_TRNS",
      "KC_TRNS",
      "KC_TRNS",
      "KC_TRNS",
      "KC_TRNS",
      "KC_TRNS",
      "KC_TRNS",
      "KC_TRNS"
    ],
    [
      "KC_TRNS",
      "KC_PIPE",
      "KC_CIRC",
      "KC_EQL",
      "KC_DLR",
      "KC_HASH",
      "KC_PERC",
      "KC_P7",
      "KC_P8",
      "KC_P9",
      "KC_ASTR",
      "ANY(TOGGLE)",
      "KC_TRNS",
      "LGUI_T(KC_DOT)",
      "LALT_T(KC_7)",
      "LSFT_T(KC_LBRC)",
      "LCTL_T(KC_RBRC)",
      "KC_AT",
      "KC_MINS",
      "LCTL_T(KC_P4)",
      "RSFT_T(KC_P5)",
      "LALT_T(KC_P6)",
      "LGUI_T(KC_SLSH)",
      "KC_TRNS",
      "KC_TRNS",
      "KC_TRNS",
      "KC_TRNS",
      "KC_TRNS",
      "KC_TRNS",
      "KC_TRNS",
      "KC_PPLS",
      "KC_P1",
      "KC_P2",
      "KC_P3",
      "KC_PENT",
      "KC_TRNS",
      "KC_TRNS",
      "KC_TRNS",
      "KC_TRNS",
      "KC_TRNS",
      "KC_TRNS",
      "KC_TRNS",
      "KC_TRNS",
      "LT(2,KC_P0)",
      "KC_TRNS",
      "KC_TRNS",
      "KC_TRNS",
      "KC_TRNS"
    ],
    [
      "KC_TRNS",
      "KC_F9",
      "KC_F10",
      "KC_F11",
      "KC_F12",
      "KC_TRNS",
      "KC_TRNS",
      "KC_TRNS",
      "KC_TRNS",
      "KC_TRNS",
      "KC_TRNS",
      "KC_TRNS",
      "KC_TRNS",
      "KC_F5",
      "KC_F6",
      "KC_F7",
      "KC_F8",
      "KC_TRNS",
      "KC_TRNS",
      "KC_LCTL",
      "KC_LSFT",
      "KC_LALT",
      "KC_LGUI",
      "KC_TRNS",
      "KC_TRNS",
      "KC_F1",
      "KC_F2",
      "KC_F3",
      "KC_F4",
      "KC_TRNS",
      "KC_TRNS",
      "KC_TRNS",
      "KC_TRNS",
      "KC_TRNS",
      "KC_TRNS",
      "KC_TRNS",
      "KC_TRNS",
      "KC_TRNS",
      "KC_TRNS",
      "KC_TRNS",
      "KC_TRNS",
      "KC_TRNS",
      "KC_TRNS",
      "KC_TRNS",
      "KC_TRNS",
      "KC_TRNS",
      "KC_TRNS",
      "KC_TRNS"
    ],
    [
      "KC_TRNS",
      "KC_ENT",
      "KC_HOME",
      "KC_UP",
      "KC_END",
      "KC_TRNS",
      "KC_TRNS",
      "KC_TRNS",
      "KC_TRNS",
      "KC_TRNS",
      "KC_TRNS",
      "KC_TRNS",
      "KC_TRNS",
      "KC_TRNS",
      "KC_LEFT",
      "KC_DOWN",
      "KC_RGHT",
      "KC_TRNS",
      "KC_TRNS",
      "KC_LCTL",
      "KC_LSFT",
      "KC_LALT",
      "KC_LGUI",
      "KC_TRNS",
      "KC_TRNS",
      "KC_TRNS",
      "KC_TRNS",
      "KC_TRNS",
      "KC_TRNS",
      "KC_TRNS",
      "KC_TRNS",
      "KC_TRNS",
      "KC_TRNS",
      "KC_TRNS",
      "KC_TRNS",
      "KC_TRNS",
      "KC_TRNS",
      "KC_TRNS",
      "KC_TRNS",
      "KC_TRNS",
      "KC_TRNS",
      "KC_TRNS",
      "KC_TRNS",
      "KC_TRNS",
      "KC_TRNS",
      "KC_TRNS",
      "KC_TRNS",
      "KC_TRNS"
    ],
    [
      "KC_TRNS",
      "KC_TRNS",
      "KC_TRNS",
      "KC_TRNS",
      "KC_TRNS",
      "KC_TRNS",
      "KC_TRNS",
      "KC_HOME",
      "KC_UP",
      "KC_END",
      "KC_TRNS",
      "KC_TRNS",
      "KC_TRNS",
      "KC_LGUI",
      "KC_LALT",
      "KC_LSFT",
      "KC_LCTL",
      "KC_TRNS",
      "KC_TRNS",
      "KC_LEFT",
      "KC_DOWN",
      "KC_RGHT",
      "KC_TRNS",
      "KC_TRNS",
      "KC_TRNS",
      "KC_TRNS",
      "KC_TRNS",
      "KC_TRNS",
      "KC_TRNS",
      "KC_TRNS",
      "KC_TRNS",
      "KC_TRNS",
      "KC_TRNS",
      "KC_TRNS",
      "KC_TRNS",
      "KC_TRNS",
      "KC_TRNS",
      "KC_TRNS",
      "KC_TRNS",
      "KC_TRNS",
      "KC_TRNS",
      "KC_TRNS",
      "KC_TRNS",
      "KC_TRNS",
      "KC_TRNS",
      "KC_TRNS",
      "KC_TRNS",
      "KC_TRNS"
    ],
    [
      "KC_TRNS",
      "TG(8)",
      "KC_BTN4",
      "KC_MS_U",
      "KC_BTN5",
      "KC_TRNS",
      "KC_TRNS",
      "KC_COPY",
      "KC_CUT",
      "KC_PSTE",
      "KC_TRNS",
      "KC_TRNS",
      "KC_TRNS",
      "KC_TRNS",
      "KC_MS_L",
      "KC_MS_D",
      "KC_MS_R",
      "KC_TRNS",
      "KC_TRNS",
      "KC_WH_D",
      "KC_WH_U",
      "KC_ACL2",
      "KC_TRNS",
      "KC_TRNS",
      "KC_TRNS",
      "KC_TRNS",
      "KC_TRNS",
      "KC_ACL0",
      "KC_ACL2",
      "KC_TRNS",
      "KC_TRNS",
      "KC_ACL0",
      "KC_TRNS",
      "KC_TRNS",
      "KC_TRNS",
      "KC_TRNS",
      "KC_TRNS",
      "KC_TRNS",
      "KC_TRNS",
      "KC_TRNS",
      "KC_TRNS",
      "KC_BTN1",
      "KC_BTN2",
      "KC_TRNS",
      "KC_TRNS",
      "KC_TRNS",
      "KC_TRNS",
      "KC_TRNS"
    ],
    [
      "KC_TRNS",
      "TG(8)",
      "KC_BTN4",
      "KC_MS_U",
      "KC_BTN5",
      "KC_TRNS",
      "KC_TRNS",
      "KC_COPY",
      "KC_CUT",
      "KC_PSTE",
      "KC_TRNS",
      "KC_TRNS",
      "KC_TRNS",
      "KC_TRNS",
      "KC_MS_L",
      "KC_MS_D",
      "KC_MS_R",
      "KC_TRNS",
      "KC_TRNS",
      "KC_WH_D",
      "KC_WH_U",
      "KC_ACL2",
      "KC_TRNS",
      "KC_TRNS",
      "KC_TRNS",
      "KC_TRNS",
      "KC_TRNS",
      "KC_TRNS",
      "KC_ACL2",
      "KC_TRNS",
      "KC_TRNS",
      "KC_TRNS",
      "KC_TRNS",
      "KC_TRNS",
      "KC_TRNS",
      "KC_TRNS",
      "KC_TRNS",
      "KC_TRNS",
      "KC_TRNS",
      "KC_TRNS",
      "KC_TRNS",
      "KC_BTN1",
      "KC_BTN2",
      "KC_TRNS",
      "KC_TRNS",
      "KC_TRNS",
      "KC_TRNS",
      "KC_TRNS"
    ],
    [
      "KC_TRNS",
      "RGB_HUD",
      "RGB_HUI",
      "RGB_VAD",
      "RGB_VAI",
      "KC_TRNS",
      "KC_TRNS",
      "KC_TRNS",
      "KC_TRNS",
      "KC_TRNS",
      "KC_TRNS",
      "KC_TRNS",
      "KC_TRNS",
      "RGB_TOG",
      "RGB_MOD",
      "RGB_SAD",
      "RGB_SAI",
      "KC_TRNS",
      "KC_TRNS",
      "KC_TRNS",
      "KC_TRNS",
      "KC_TRNS",
      "KC_TRNS",
      "KC_TRNS",
      "KC_TRNS",
      "KC_TRNS",
      "KC_TRNS",
      "KC_TRNS",
      "KC_TRNS",
      "KC_TRNS",
      "KC_TRNS",
      "KC_TRNS",
      "KC_TRNS",
      "KC_TRNS",
      "KC_TRNS",
      "KC_TRNS",
      "RESET",
      "KC_TRNS",
      "KC_TRNS",
      "KC_TRNS",
      "KC_TRNS",
      "KC_TRNS",
      "KC_TRNS",
      "KC_TRNS",
      "KC_TRNS",
      "KC_TRNS",
      "KC_TRNS",
      "KC_TRNS"
    ],
    [
      "KC_TRNS",
      "KC_TRNS",
      "KC_MPLY",
      "KC_VOLU",
      "KC_MUTE",
      "KC_TRNS",
      "KC_TRNS",
      "KC_TRNS",
      "KC_TRNS",
      "KC_TRNS",
      "KC_TRNS",
      "KC_TRNS",
      "KC_TRNS",
      "KC_TRNS",
      "KC_MPRV",
      "KC_VOLD",
      "KC_MNXT",
      "KC_TRNS",
      "KC_TRNS",
      "KC_TRNS",
      "KC_TRNS",
      "KC_TRNS",
      "KC_TRNS",
      "KC_TRNS",
      "KC_TRNS",
      "KC_TRNS",
      "KC_TRNS",
      "KC_TRNS",
      "KC_TRNS",
      "KC_TRNS",
      "KC_TRNS",
      "KC_TRNS",
      "KC_TRNS",
      "KC_TRNS",
      "KC_TRNS",
      "KC_TRNS",
      "KC_TRNS",
      "KC_TRNS",
      "KC_TRNS",
      "KC_TRNS",
      "KC_TRNS",
      "KC_TRNS",
      "KC_TRNS",
      "KC_TRNS",
      "KC_TRNS",
      "KC_TRNS",
      "KC_TRNS",
      "KC_TRNS"
    ]
  ],
  "author": ""
}